seekly.py
seekly/__init__.py
seekly/file_processor.py
seekly/model.py
seekly/search.py
seekly/spinner.py
seekly/tests/test_files/addition.cpp
seekly/tests/test_files/odd_even.py
seekly/tests/test_files/prime.go
seekly/tests/test_files/search.js
seekly/tests/test_files/sort.java
seekly/tests/test_files/subtraction.c
seekly/tests/test_files/utils.js
seekly/tests/test_files/utils.rs
seekly-1.1.2.dist-info/licenses/LICENSE
seekly-1.1.2.dist-info/METADATA
seekly-1.1.2.dist-info/WHEEL
seekly-1.1.2.dist-info/entry_points.txt
seekly-1.1.2.dist-info/top_level.txt
seekly-1.1.2.dist-info/RECORD
