Metadata-Version: 2.4
Name: seekly
Version: 1.1.2
Summary: Natural language search for files using semantic code understanding
Home-page: https://github.com/Dhodraj/seekly
Author: Dhodraj Sundaram
Author-email: Dhodraj Sundaram <dhodrajsdr192@gmail.com>
License: MIT
Project-URL: Repository, https://github.com/Dhodraj/seekly
Project-URL: Issues, https://github.com/Dhodraj/seekly/issues
Classifier: Programming Language :: Python :: 3
Classifier: Operating System :: OS Independent
Requires-Python: >=3.8
License-File: LICENSE
Requires-Dist: transformers>=4.30.0
Requires-Dist: torch>=2.0.0
Requires-Dist: numpy>=1.22.0
Requires-Dist: click>=8.0.0
Requires-Dist: pathlib>=1.0.1
Requires-Dist: tqdm>=4.65.0
Requires-Dist: sentence-transformers>=2.2.2
Dynamic: author
Dynamic: home-page
Dynamic: license-file
Dynamic: requires-python
